ciuv/__init__.py
ciuv/decorators/singleton.py
ciuv-0.1.1.dist-info/WHEEL
ciuv-0.1.1.dist-info/entry_points.txt
ciuv-0.1.1.dist-info/METADATA
ciuv-0.1.1.dist-info/RECORD
